bcTeams/__init__.py
bcTeams/db.py
bcTeam-0.0.4.dist-info/LICENSE
bcTeam-0.0.4.dist-info/METADATA
bcTeam-0.0.4.dist-info/WHEEL
bcTeam-0.0.4.dist-info/top_level.txt
bcTeam-0.0.4.dist-info/RECORD
