Metadata-Version: 2.1
Name: bcTeam
Version: 0.0.4
Summary: . . .
Author-email: Ali Zolg <alizolglib@gmail.com>
License: Copyright (c) 2024 Ali Zolg
Project-URL: Homepage, https://github.com/pypa/sampleproject
Project-URL: Bug Tracker, https://github.com/pypa/sampleproject/issues
Classifier: Programming Language :: Python :: 3
Classifier: License :: OSI Approved :: MIT License
Classifier: Operating System :: OS Independent
Requires-Python: >=3.7
License-File: LICENSE
